docs/source/conf.py
molSimplify/__init__.py
molSimplify/__main__.py
molSimplify/Bind/bind.dict
molSimplify/Classes/__init__.py
molSimplify/Classes/atom3D.py
molSimplify/Classes/dft_obs.py
molSimplify/Classes/globalvars.py
molSimplify/Classes/helpers.py
molSimplify/Classes/ligand.py
molSimplify/Classes/mol2D.py
molSimplify/Classes/mol3D.py
molSimplify/Classes/monomer3D.py
molSimplify/Classes/partialcharges.py
molSimplify/Classes/protein3D.py
molSimplify/Classes/rundiag.py
molSimplify/Classes/voxelgrid.py
molSimplify/Cores/cores.dict
molSimplify/Data/ML.dat
molSimplify/Data/MLS_FSR_for_inter.dat
molSimplify/Data/MLS_FSR_for_inter2.dat
molSimplify/Data/MLS_angle_for_click.dat
molSimplify/Data/MLS_angle_for_inter.dat
molSimplify/Data/MLS_angle_for_inter2.dat
molSimplify/Data/MLS_angle_for_intra.dat
molSimplify/Data/MLS_angle_for_intra2.dat
molSimplify/Data/MLS_angle_for_oa.dat
molSimplify/Data/ML_FSR_for_inter.dat
molSimplify/Data/ML_FSR_for_inter2.dat
molSimplify/Data/ML_bond_for_cat.dat
molSimplify/Data/ML_bond_for_click.dat
molSimplify/Data/ML_bond_for_inter.dat
molSimplify/Data/ML_bond_for_inter2.dat
molSimplify/Data/ML_bond_for_intra.dat
molSimplify/Data/ML_bond_for_intra2.dat
molSimplify/Data/ML_bond_for_oa.dat
molSimplify/Data/bp1.dat
molSimplify/Data/coordinations.dict
molSimplify/Data/li.dat
molSimplify/Data/no.dat
molSimplify/Data/oct.dat
molSimplify/Data/pbp.dat
molSimplify/Data/spy.dat
molSimplify/Data/sqap.dat
molSimplify/Data/sqp.dat
molSimplify/Data/tbp.dat
molSimplify/Data/tdhd.dat
molSimplify/Data/thd.dat
molSimplify/Data/tpl.dat
molSimplify/Data/tpr.dat
molSimplify/Informatics/Mol2Parser.py
molSimplify/Informatics/RACassemble.py
molSimplify/Informatics/__init__.py
molSimplify/Informatics/autocorrelation.py
molSimplify/Informatics/coulomb_analyze.py
molSimplify/Informatics/decoration_manager.py
molSimplify/Informatics/geo_analyze.py
molSimplify/Informatics/geometrics.py
molSimplify/Informatics/graph_analyze.py
molSimplify/Informatics/graph_racs.py
molsimplify-1.8.0.dist-info/licenses/LICENSE
molsimplify-1.8.0.dist-info/METADATA
molsimplify-1.8.0.dist-info/WHEEL
molsimplify-1.8.0.dist-info/entry_points.txt
molsimplify-1.8.0.dist-info/top_level.txt
molsimplify-1.8.0.dist-info/RECORD
