Metadata-Version: 2.4
Name: molSimplify
Version: 1.8.0
License:                     GNU GENERAL PUBLIC LICENSE
Project-URL: Homepage, https://molsimplify.mit.edu/
Project-URL: Documentation, http://hjkgrp.mit.edu/molsimplify-tutorials/
Project-URL: Repository, https://github.com/hjkgrp/molSimplify
License-File: LICENSE
Requires-Dist: openbabel-wheel
Requires-Dist: numpy
Requires-Dist: scipy
Requires-Dist: pandas
Requires-Dist: networkx>=2.7
Requires-Dist: scikit-learn
Requires-Dist: keras
Requires-Dist: tensorflow
Requires-Dist: pyyaml
Requires-Dist: importlib-resources
Provides-Extra: dev
Requires-Dist: pytest; extra == "dev"
Requires-Dist: pytest-resource-path; extra == "dev"
Requires-Dist: pre-commit; extra == "dev"
Provides-Extra: docs
Requires-Dist: beautifulsoup4; extra == "docs"
Requires-Dist: sphinx; extra == "docs"
Requires-Dist: readthedocs-sphinx-ext; extra == "docs"
Requires-Dist: sphinx_rtd_theme; extra == "docs"
Dynamic: license-file
